{"@context":{"@language":"en","@vocab":"https://schema.org/","citeAs":"cr:citeAs","column":"cr:column","conformsTo":"dct:conformsTo","cr":"http://mlcommons.org/croissant/","data":{"@id":"cr:data","@type":"@json"},"dataBiases":"cr:dataBiases","dataCollection":"cr:dataCollection","dataType":{"@id":"cr:dataType","@type":"@vocab"},"dct":"http://purl.org/dc/terms/","extract":"cr:extract","field":"cr:field","fileProperty":"cr:fileProperty","fileObject":"cr:fileObject","fileSet":"cr:fileSet","format":"cr:format","includes":"cr:includes","isEnumeration":"cr:isEnumeration","isLiveDataset":"cr:isLiveDataset","jsonPath":"cr:jsonPath","key":"cr:key","md5":"cr:md5","parentField":"cr:parentField","path":"cr:path","personalSensitiveInformation":"cr:personalSensitiveInformation","recordSet":"cr:recordSet","references":"cr:references","regex":"cr:regex","repeated":"cr:repeated","replace":"cr:replace","sc":"https://schema.org/","separator":"cr:separator","source":"cr:source","subField":"cr:subField","transform":"cr:transform","wd":"https://www.wikidata.org/wiki/"},"alternateName":"~225.000 Age of Empires 2: DE matches on multiple levels of granularity","conformsTo":"http://mlcommons.org/croissant/1.0","license":{"@type":"sc:CreativeWork","name":"Attribution-NonCommercial 4.0 International (CC BY-NC 4.0)","url":"https://creativecommons.org/licenses/by-nc/4.0/"},"distribution":[{"contentUrl":"https://www.kaggle.com/api/v1/datasets/download/nicoelbert/aoe-matchups?datasetVersionNumber=6","contentSize":"12.702 GB","md5":"kEduNVl8JaxSH5lGcINxDg==","encodingFormat":"application/zip","@id":"archive.zip","@type":"cr:FileObject","name":"archive.zip","description":"Archive containing all the contents of the Age of Empires 2: DE Match Data dataset"},{"includes":"*.csv","containedIn":{"@id":"archive.zip"},"encodingFormat":"text/csv","@id":"text-csv_fileset","@type":"cr:FileSet","name":"text/csv files","description":"text/csv files contained in archive.zip"}],"version":6,"keywords":["data type \u003E tabular","subject \u003E culture and humanities \u003E games","subject \u003E culture and humanities \u003E games \u003E video games"],"isAccessibleForFree":true,"includedInDataCatalog":{"@type":"sc:DataCatalog","name":"Kaggle","url":"https://www.kaggle.com"},"creator":{"@type":"sc:Person","name":"Nico Elbert","url":"/nicoelbert","image":"https://storage.googleapis.com/kaggle-avatars/thumbnails/default-thumb.png"},"publisher":{"@type":"sc:Organization","name":"Kaggle","url":"https://www.kaggle.com/organizations/kaggle","image":"https://storage.googleapis.com/kaggle-organizations/4/thumbnail.png"},"thumbnailUrl":"https://storage.googleapis.com/kaggle-datasets-images/2600973/4441689/d0c87593de4d318923c72d9ae0a92b69/dataset-card.jpeg?t=2022-11-04-22-28-20","dateModified":"2022-11-07T12:57:34.56","datePublished":"2022-11-03T07:12:23.317","@type":"sc:Dataset","name":"Age of Empires 2: DE Match Data","url":"https://www.kaggle.com/datasets/nicoelbert/aoe-matchups/versions/6","description":"The dataset contains roughly 225.000 matches played in Age of Empires 2: Definitive Edition in different granularity and connected Master Data.\nThe current version contains 3 levels:\n-Match Level: featuring Match Id, Map, Map Size, Duration, Mean Elo, Civilizations, Starting Positions and Outcomes with one row per game\n-Time Slice Level: contains the aggregated commands of type \u0022Queue\u0022,\u0022Build\u0022 and \u0022Research\u0022 made until a certain time in the game, with one row per game and one file per time slice. The games are sliced in 120 second slices. \n-Input Level: contains data about all made decisions in a game, with one row per input and one file per game.  \n\nThe information were collected by scraping and parsing AoE2:DE matches, using https://github.com/happyleavesaoc/aoc-mgz. The code for the underlying work can be found in https://github.com/nicoelbert/rtsgamestates.\n\nStay posted, for any questions feel free to get in touch. \n"}